dot/__init__.py
dot/__main__.py
dot/config.py
dot/controllers/__init__.py
dot/controllers/base_controller.py
dot/controllers/clean_controller.py
dot/controllers/clone_controller.py
dot/controllers/pull_controller.py
dot/controllers/push_controller.py
dot/controllers/stage_controller.py
dot/controllers/symlink_controller.py
dot/controllers/sync_controller.py
dot/services/__init__.py
dot/services/dot_service.py
dot/services/git_service.py
dot/services/print_service.py
dotcli-0.1.7.dist-info/DESCRIPTION.rst
dotcli-0.1.7.dist-info/METADATA
dotcli-0.1.7.dist-info/RECORD
dotcli-0.1.7.dist-info/WHEEL
dotcli-0.1.7.dist-info/entry_points.txt
dotcli-0.1.7.dist-info/metadata.json
dotcli-0.1.7.dist-info/top_level.txt
