Metadata-Version: 2.0
Name: dotcli
Version: 0.1.7
Summary: A git inspired CLI to manage your dotfiles
Home-page: https://github.com/jamrizzi/dot
Author: Jam Risser
Author-email: jam@jamrizzi.com
License: MIT
Keywords: cli git github dot dotfiles sync symlink command line
Platform: UNKNOWN
Classifier: Development Status :: 4 - Beta
Classifier: Intended Audience :: Developers
Classifier: Topic :: Utilities
Classifier: License :: OSI Approved :: MIT License
Classifier: Programming Language :: Python :: 2
Classifier: Programming Language :: Python :: 2.7
Classifier: Programming Language :: Python :: 3
Classifier: Programming Language :: Python :: 3.3
Classifier: Programming Language :: Python :: 3.4
Classifier: Programming Language :: Python :: 3.5
Requires-Dist: GitPython (==2.1.5)
Requires-Dist: PyYAML (==3.12)
Requires-Dist: cement (==2.10.2)
Requires-Dist: futures (==3.1.1)
Requires-Dist: gitdb2 (==2.0.2)
Requires-Dist: pyspin (==1.1.1)
Requires-Dist: six (==1.10.0)
Requires-Dist: smmap2 (==2.0.3)
